mypackage/__init__.py
mypackage/mypackage.py
mVedr-0.0.3.dist-info/METADATA
mVedr-0.0.3.dist-info/WHEEL
mVedr-0.0.3.dist-info/top_level.txt
mVedr-0.0.3.dist-info/RECORD
