Metadata-Version: 2.1
Name: mVedr
Version: 0.0.3
Summary: My first package
